selfauth/__init__.py
selfauth/apps.py
selfauth/auth.py
selfauth/models.py
selfauth/signals.py
selfauth/urls.py
selfauth/views.py
selfauth-1.1.0.dist-info/LICENSE.md
selfauth-1.1.0.dist-info/METADATA
selfauth-1.1.0.dist-info/WHEEL
selfauth-1.1.0.dist-info/top_level.txt
selfauth-1.1.0.dist-info/RECORD
