Metadata-Version: 2.1
Name: selfauth
Version: 1.1.0
Summary: Self Street integration with Django for SSO.
Home-page: https://github.com/column-street/django-self-auth
Author: Felipe Faria
Author-email: felipe@self.st
License: BSD 3-Clause License
Keywords: django-self-auth
Platform: UNKNOWN
Classifier: Environment :: Web Environment
Classifier: Framework :: Django
Classifier: Intended Audience :: Developers
Classifier: License :: OSI Approved :: BSD License
Classifier: Operating System :: OS Independent
Classifier: Programming Language :: Python
Classifier: Programming Language :: Python :: 3
Classifier: Programming Language :: Python :: 3 :: Only
Classifier: Programming Language :: Python :: 3.6
Classifier: Programming Language :: Python :: 3.7
Classifier: Programming Language :: Python :: 3.8
Classifier: Topic :: Internet :: WWW/HTTP
Classifier: Topic :: Internet :: WWW/HTTP :: Dynamic Content
Requires-Dist: Django (>=3.0.0)
Requires-Dist: mozilla-django-oidc (>=1.2.4)
Requires-Dist: phonenumbers (>=8.12.9)
